{
  "id": "",
  "name": "",
  "font_family": "iconfont",
  "css_prefix_text": "icon-",
  "description": "",
  "glyphs": [
    {
      "icon_id": "52679802",
      "name": "ipad",
      "font_class": "ipad",
      "unicode": "e792",
      "unicode_decimal": 59282
    },
    {
      "icon_id": "52679804",
      "name": "integral",
      "font_class": "integral1",
      "unicode": "e794",
      "unicode_decimal": 59284
    },
    {
      "icon_id": "52679805",
      "name": "kitchen",
      "font_class": "kitchen",
      "unicode": "e795",
      "unicode_decimal": 59285
    },
    {
      "icon_id": "52679806",
      "name": "inquiry-template",
      "font_class": "inquiry-template",
      "unicode": "e796",
      "unicode_decimal": 59286
    },
    {
      "icon_id": "52679807",
      "name": "link",
      "font_class": "link",
      "unicode": "e797",
      "unicode_decimal": 59287
    },
    {
      "icon_id": "52679808",
      "name": "libra",
      "font_class": "libra",
      "unicode": "e798",
      "unicode_decimal": 59288
    },
    {
      "icon_id": "52679811",
      "name": "lights",
      "font_class": "lights",
      "unicode": "e79b",
      "unicode_decimal": 59291
    },
    {
      "icon_id": "52679812",
      "name": "logistics-icon",
      "font_class": "logistics-icon",
      "unicode": "e79c",
      "unicode_decimal": 59292
    },
    {
      "icon_id": "52679813",
      "name": "message center",
      "font_class": "messagecenter",
      "unicode": "e79d",
      "unicode_decimal": 59293
    },
    {
      "icon_id": "52679814",
      "name": "mobile-phone",
      "font_class": "mobile-phone",
      "unicode": "e79e",
      "unicode_decimal": 59294
    },
    {
      "icon_id": "52679815",
      "name": "manage-order",
      "font_class": "manage-order",
      "unicode": "e79f",
      "unicode_decimal": 59295
    },
    {
      "icon_id": "52679816",
      "name": "move",
      "font_class": "move",
      "unicode": "e7a0",
      "unicode_decimal": 59296
    },
    {
      "icon_id": "52679817",
      "name": "Money management",
      "font_class": "Moneymanagement",
      "unicode": "e7a1",
      "unicode_decimal": 59297
    },
    {
      "icon_id": "52679818",
      "name": "namecard",
      "font_class": "namecard",
      "unicode": "e7a2",
      "unicode_decimal": 59298
    },
    {
      "icon_id": "52679819",
      "name": "map",
      "font_class": "map",
      "unicode": "e7a3",
      "unicode_decimal": 59299
    },
    {
      "icon_id": "52679820",
      "name": "New user zone",
      "font_class": "Newuserzone",
      "unicode": "e7a4",
      "unicode_decimal": 59300
    },
    {
      "icon_id": "52679821",
      "name": "multi-language",
      "font_class": "multi-language",
      "unicode": "e7a5",
      "unicode_decimal": 59301
    },
    {
      "icon_id": "52679822",
      "name": "office",
      "font_class": "office",
      "unicode": "e7a6",
      "unicode_decimal": 59302
    },
    {
      "icon_id": "52679823",
      "name": "notice",
      "font_class": "notice",
      "unicode": "e7a7",
      "unicode_decimal": 59303
    },
    {
      "icon_id": "52679824",
      "name": "on time shipment",
      "font_class": "ontimeshipment",
      "unicode": "e7a8",
      "unicode_decimal": 59304
    },
    {
      "icon_id": "52679825",
      "name": "office-supplies",
      "font_class": "office-supplies",
      "unicode": "e7a9",
      "unicode_decimal": 59305
    },
    {
      "icon_id": "52679826",
      "name": "password",
      "font_class": "password",
      "unicode": "e7aa",
      "unicode_decimal": 59306
    },
    {
      "icon_id": "52679827",
      "name": "Not visible",
      "font_class": "Notvisible1",
      "unicode": "e7ab",
      "unicode_decimal": 59307
    },
    {
      "icon_id": "52679829",
      "name": "packaging",
      "font_class": "packaging",
      "unicode": "e7ad",
      "unicode_decimal": 59309
    },
    {
      "icon_id": "52679830",
      "name": "online-tracking",
      "font_class": "online-tracking",
      "unicode": "e7ae",
      "unicode_decimal": 59310
    },
    {
      "icon_id": "52679831",
      "name": "packing-labeling",
      "font_class": "packing-labeling",
      "unicode": "e7af",
      "unicode_decimal": 59311
    },
    {
      "icon_id": "52679832",
      "name": "phone",
      "font_class": "phone",
      "unicode": "e7b0",
      "unicode_decimal": 59312
    },
    {
      "icon_id": "52679833",
      "name": "pic",
      "font_class": "pic1",
      "unicode": "e7b1",
      "unicode_decimal": 59313
    },
    {
      "icon_id": "52679835",
      "name": "play",
      "font_class": "play1",
      "unicode": "e7b3",
      "unicode_decimal": 59315
    },
    {
      "icon_id": "52679836",
      "name": "logistic-logo",
      "font_class": "logistic-logo",
      "unicode": "e7b4",
      "unicode_decimal": 59316
    },
    {
      "icon_id": "52679838",
      "name": "product",
      "font_class": "product",
      "unicode": "e7b6",
      "unicode_decimal": 59318
    },
    {
      "icon_id": "52679839",
      "name": "machinery",
      "font_class": "machinery",
      "unicode": "e7b7",
      "unicode_decimal": 59319
    },
    {
      "icon_id": "52679840",
      "name": "process",
      "font_class": "process",
      "unicode": "e7b8",
      "unicode_decimal": 59320
    },
    {
      "icon_id": "52679841",
      "name": "prompt",
      "font_class": "prompt",
      "unicode": "e7b9",
      "unicode_decimal": 59321
    },
    {
      "icon_id": "52679842",
      "name": "QRcode",
      "font_class": "QRcode1",
      "unicode": "e7ba",
      "unicode_decimal": 59322
    },
    {
      "icon_id": "52679845",
      "name": "Non-staple food",
      "font_class": "Non-staplefood",
      "unicode": "e7bd",
      "unicode_decimal": 59325
    },
    {
      "icon_id": "52679846",
      "name": "rejected-order",
      "font_class": "rejected-order",
      "unicode": "e7be",
      "unicode_decimal": 59326
    },
    {
      "icon_id": "52679848",
      "name": "remind",
      "font_class": "remind",
      "unicode": "e7c0",
      "unicode_decimal": 59328
    },
    {
      "icon_id": "52679849",
      "name": "response time",
      "font_class": "responsetime",
      "unicode": "e7c1",
      "unicode_decimal": 59329
    },
    {
      "icon_id": "52679851",
      "name": "paylater",
      "font_class": "paylater",
      "unicode": "e7c3",
      "unicode_decimal": 59331
    },
    {
      "icon_id": "52679854",
      "name": "rmb",
      "font_class": "rmb1",
      "unicode": "e7c6",
      "unicode_decimal": 59334
    },
    {
      "icon_id": "52679855",
      "name": "RFQ-logo",
      "font_class": "RFQ-logo",
      "unicode": "e7c7",
      "unicode_decimal": 59335
    },
    {
      "icon_id": "52679856",
      "name": "save",
      "font_class": "save",
      "unicode": "e7c8",
      "unicode_decimal": 59336
    },
    {
      "icon_id": "52679857",
      "name": "scanning",
      "font_class": "scanning",
      "unicode": "e7c9",
      "unicode_decimal": 59337
    },
    {
      "icon_id": "52679858",
      "name": "security",
      "font_class": "security",
      "unicode": "e7ca",
      "unicode_decimal": 59338
    },
    {
      "icon_id": "52679859",
      "name": "sales center",
      "font_class": "salescenter",
      "unicode": "e7cb",
      "unicode_decimal": 59339
    },
    {
      "icon_id": "52679862",
      "name": "raw",
      "font_class": "raw",
      "unicode": "e7ce",
      "unicode_decimal": 59342
    },
    {
      "icon_id": "52679863",
      "name": "service",
      "font_class": "service",
      "unicode": "e7cf",
      "unicode_decimal": 59343
    },
    {
      "icon_id": "52679864",
      "name": "share",
      "font_class": "share",
      "unicode": "e7d0",
      "unicode_decimal": 59344
    },
    {
      "icon_id": "52679865",
      "name": "signboard",
      "font_class": "signboard",
      "unicode": "e7d1",
      "unicode_decimal": 59345
    },
    {
      "icon_id": "52679866",
      "name": "shuffling-banner",
      "font_class": "shuffling-banner",
      "unicode": "e7d2",
      "unicode_decimal": 59346
    },
    {
      "icon_id": "52679867",
      "name": "Right button",
      "font_class": "Rightbutton",
      "unicode": "e7d3",
      "unicode_decimal": 59347
    },
    {
      "icon_id": "52679869",
      "name": "sound-Mute",
      "font_class": "sound-Mute",
      "unicode": "e7d5",
      "unicode_decimal": 59349
    },
    {
      "icon_id": "52679870",
      "name": "category products",
      "font_class": "Similarproducts",
      "unicode": "e7d6",
      "unicode_decimal": 59350
    },
    {
      "icon_id": "52679871",
      "name": "sound-filling",
      "font_class": "sound-filling",
      "unicode": "e7d7",
      "unicode_decimal": 59351
    },
    {
      "icon_id": "52679872",
      "name": "suggest",
      "font_class": "suggest",
      "unicode": "e7d8",
      "unicode_decimal": 59352
    },
    {
      "icon_id": "52679873",
      "name": "stop",
      "font_class": "stop",
      "unicode": "e7d9",
      "unicode_decimal": 59353
    },
    {
      "icon_id": "52679875",
      "name": "supplier-features",
      "font_class": "supplier-features",
      "unicode": "e7db",
      "unicode_decimal": 59355
    },
    {
      "icon_id": "52679877",
      "name": "survey",
      "font_class": "survey",
      "unicode": "e7dd",
      "unicode_decimal": 59357
    },
    {
      "icon_id": "52679878",
      "name": "template",
      "font_class": "template",
      "unicode": "e7de",
      "unicode_decimal": 59358
    },
    {
      "icon_id": "52679879",
      "name": "text",
      "font_class": "text",
      "unicode": "e7df",
      "unicode_decimal": 59359
    },
    {
      "icon_id": "52679880",
      "name": "suspended",
      "font_class": "suspended",
      "unicode": "e7e0",
      "unicode_decimal": 59360
    },
    {
      "icon_id": "52679881",
      "name": "task-management",
      "font_class": "task-management",
      "unicode": "e7e1",
      "unicode_decimal": 59361
    },
    {
      "icon_id": "52679882",
      "name": "tool",
      "font_class": "tool",
      "unicode": "e7e2",
      "unicode_decimal": 59362
    },
    {
      "icon_id": "52679883",
      "name": "top",
      "font_class": "Top",
      "unicode": "e7e3",
      "unicode_decimal": 59363
    },
    {
      "icon_id": "52679885",
      "name": "textile-products",
      "font_class": "textile-products",
      "unicode": "e7e5",
      "unicode_decimal": 59365
    },
    {
      "icon_id": "52679886",
      "name": "trade alert",
      "font_class": "tradealert",
      "unicode": "e7e6",
      "unicode_decimal": 59366
    },
    {
      "icon_id": "52679887",
      "name": "top sales",
      "font_class": "topsales",
      "unicode": "e7e7",
      "unicode_decimal": 59367
    },
    {
      "icon_id": "52679888",
      "name": "trading volume",
      "font_class": "tradingvolume",
      "unicode": "e7e8",
      "unicode_decimal": 59368
    },
    {
      "icon_id": "52679889",
      "name": "training",
      "font_class": "training",
      "unicode": "e7e9",
      "unicode_decimal": 59369
    },
    {
      "icon_id": "52679890",
      "name": "upload",
      "font_class": "upload",
      "unicode": "e7ea",
      "unicode_decimal": 59370
    },
    {
      "icon_id": "52679893",
      "name": "viewgallery",
      "font_class": "viewgallery",
      "unicode": "e7ed",
      "unicode_decimal": 59373
    },
    {
      "icon_id": "52679894",
      "name": "vehivles",
      "font_class": "vehivles",
      "unicode": "e7ee",
      "unicode_decimal": 59374
    },
    {
      "icon_id": "52679895",
      "name": "trust",
      "font_class": "trust",
      "unicode": "e7ef",
      "unicode_decimal": 59375
    },
    {
      "icon_id": "52679896",
      "name": "warning",
      "font_class": "warning",
      "unicode": "e7f0",
      "unicode_decimal": 59376
    },
    {
      "icon_id": "52679897",
      "name": "warehouse",
      "font_class": "warehouse",
      "unicode": "e7f1",
      "unicode_decimal": 59377
    },
    {
      "icon_id": "52679899",
      "name": "video",
      "font_class": "video",
      "unicode": "e7f3",
      "unicode_decimal": 59379
    },
    {
      "icon_id": "52679900",
      "name": "viewlist",
      "font_class": "viewlist",
      "unicode": "e7f4",
      "unicode_decimal": 59380
    },
    {
      "icon_id": "52679901",
      "name": "set",
      "font_class": "set",
      "unicode": "e7f5",
      "unicode_decimal": 59381
    },
    {
      "icon_id": "52679902",
      "name": "store",
      "font_class": "store",
      "unicode": "e7f6",
      "unicode_decimal": 59382
    },
    {
      "icon_id": "52679903",
      "name": "tool-hardware",
      "font_class": "tool-hardware",
      "unicode": "e7f7",
      "unicode_decimal": 59383
    },
    {
      "icon_id": "52679904",
      "name": "vs",
      "font_class": "vs",
      "unicode": "e7f8",
      "unicode_decimal": 59384
    },
    {
      "icon_id": "52679905",
      "name": "toy",
      "font_class": "toy",
      "unicode": "e7f9",
      "unicode_decimal": 59385
    },
    {
      "icon_id": "52679907",
      "name": "credit card",
      "font_class": "creditcard",
      "unicode": "e7fb",
      "unicode_decimal": 59387
    },
    {
      "icon_id": "52679908",
      "name": "contacts",
      "font_class": "contacts",
      "unicode": "e7fc",
      "unicode_decimal": 59388
    },
    {
      "icon_id": "52679909",
      "name": "checkstand",
      "font_class": "checkstand",
      "unicode": "e7fd",
      "unicode_decimal": 59389
    },
    {
      "icon_id": "52679910",
      "name": "aviation",
      "font_class": "aviation",
      "unicode": "e7fe",
      "unicode_decimal": 59390
    },
    {
      "icon_id": "52679911",
      "name": "Daytime mode",
      "font_class": "Daytimemode",
      "unicode": "e7ff",
      "unicode_decimal": 59391
    },
    {
      "icon_id": "52679913",
      "name": "discounts",
      "font_class": "discounts",
      "unicode": "e801",
      "unicode_decimal": 59393
    },
    {
      "icon_id": "52679914",
      "name": "invoice",
      "font_class": "invoice",
      "unicode": "e802",
      "unicode_decimal": 59394
    },
    {
      "icon_id": "52679915",
      "name": "insurance",
      "font_class": "insurance",
      "unicode": "e803",
      "unicode_decimal": 59395
    },
    {
      "icon_id": "52679917",
      "name": "user center",
      "font_class": "usercenter",
      "unicode": "e805",
      "unicode_decimal": 59397
    },
    {
      "icon_id": "52679918",
      "name": "unlock",
      "font_class": "unlock",
      "unicode": "e806",
      "unicode_decimal": 59398
    },
    {
      "icon_id": "52679919",
      "name": "vip",
      "font_class": "vip",
      "unicode": "e807",
      "unicode_decimal": 59399
    },
    {
      "icon_id": "52679920",
      "name": "wallet",
      "font_class": "wallet",
      "unicode": "e808",
      "unicode_decimal": 59400
    },
    {
      "icon_id": "52679921",
      "name": "land transportation",
      "font_class": "landtransportation",
      "unicode": "e809",
      "unicode_decimal": 59401
    },
    {
      "icon_id": "52679922",
      "name": "voice",
      "font_class": "voice",
      "unicode": "e80a",
      "unicode_decimal": 59402
    },
    {
      "icon_id": "52679924",
      "name": "contacts-fill",
      "font_class": "contacts-fill",
      "unicode": "e80c",
      "unicode_decimal": 59404
    },
    {
      "icon_id": "52679925",
      "name": "add-account",
      "font_class": "add-account1",
      "unicode": "e80d",
      "unicode_decimal": 59405
    },
    {
      "icon_id": "52679926",
      "name": "2years-fill",
      "font_class": "years-fill",
      "unicode": "e80e",
      "unicode_decimal": 59406
    },
    {
      "icon_id": "52679928",
      "name": "add-fill",
      "font_class": "add-fill",
      "unicode": "e810",
      "unicode_decimal": 59408
    },
    {
      "icon_id": "52679929",
      "name": "all-fill",
      "font_class": "all-fill1",
      "unicode": "e811",
      "unicode_decimal": 59409
    },
    {
      "icon_id": "52679931",
      "name": "calendar-fill",
      "font_class": "calendar-fill",
      "unicode": "e813",
      "unicode_decimal": 59411
    },
    {
      "icon_id": "52679932",
      "name": "bad-fill",
      "font_class": "bad-fill",
      "unicode": "e814",
      "unicode_decimal": 59412
    },
    {
      "icon_id": "52679933",
      "name": "bussiness-man-fill",
      "font_class": "bussiness-man-fill",
      "unicode": "e815",
      "unicode_decimal": 59413
    },
    {
      "icon_id": "52679934",
      "name": "atm-fill",
      "font_class": "atm-fill",
      "unicode": "e816",
      "unicode_decimal": 59414
    },
    {
      "icon_id": "52680057",
      "name": "quick",
      "font_class": "quick",
      "unicode": "e891",
      "unicode_decimal": 59537
    },
    {
      "icon_id": "52680058",
      "name": "writing",
      "font_class": "writing",
      "unicode": "e892",
      "unicode_decimal": 59538
    },
    {
      "icon_id": "52680061",
      "name": "gif-fill",
      "font_class": "gifjpge-fill",
      "unicode": "e895",
      "unicode_decimal": 59541
    },
    {
      "icon_id": "52680065",
      "name": "home",
      "font_class": "Hometextile",
      "unicode": "e899",
      "unicode_decimal": 59545
    },
    {
      "icon_id": "52680066",
      "name": "home",
      "font_class": "home",
      "unicode": "e89a",
      "unicode_decimal": 59546
    },
    {
      "icon_id": "52680067",
      "name": "send inquiry-fill",
      "font_class": "sendinquiry-fill",
      "unicode": "e89b",
      "unicode_decimal": 59547
    },
    {
      "icon_id": "52680068",
      "name": "comments-fill",
      "font_class": "comments-fill",
      "unicode": "e89c",
      "unicode_decimal": 59548
    },
    {
      "icon_id": "52680069",
      "name": "account-fill",
      "font_class": "account-fill",
      "unicode": "e89d",
      "unicode_decimal": 59549
    },
    {
      "icon_id": "52680070",
      "name": "feed-logo-fill",
      "font_class": "feed-logo-fill",
      "unicode": "e89e",
      "unicode_decimal": 59550
    },
    {
      "icon_id": "52680071",
      "name": "feed-logo",
      "font_class": "feed-logo",
      "unicode": "e89f",
      "unicode_decimal": 59551
    },
    {
      "icon_id": "52680072",
      "name": "home-fill",
      "font_class": "home-fill",
      "unicode": "e8a0",
      "unicode_decimal": 59552
    },
    {
      "icon_id": "52680075",
      "name": "camera",
      "font_class": "camera",
      "unicode": "e8a3",
      "unicode_decimal": 59555
    },
    {
      "icon_id": "52680077",
      "name": "account",
      "font_class": "account",
      "unicode": "e8a5",
      "unicode_decimal": 59557
    },
    {
      "icon_id": "52680078",
      "name": "comments",
      "font_class": "comments",
      "unicode": "e8a6",
      "unicode_decimal": 59558
    },
    {
      "icon_id": "52680079",
      "name": "cart-Empty",
      "font_class": "cart-Empty1",
      "unicode": "e8a7",
      "unicode_decimal": 59559
    },
    {
      "icon_id": "52680081",
      "name": "order",
      "font_class": "order",
      "unicode": "e8a9",
      "unicode_decimal": 59561
    },
    {
      "icon_id": "52680083",
      "name": "trade-assurance",
      "font_class": "trade-assurance",
      "unicode": "e8ab",
      "unicode_decimal": 59563
    },
    {
      "icon_id": "52680084",
      "name": "user center",
      "font_class": "usercenter1",
      "unicode": "e8ac",
      "unicode_decimal": 59564
    },
    {
      "icon_id": "52680085",
      "name": "trading data",
      "font_class": "tradingdata",
      "unicode": "e8ad",
      "unicode_decimal": 59565
    },
    {
      "icon_id": "52680087",
      "name": "txt",
      "font_class": "txt",
      "unicode": "e8af",
      "unicode_decimal": 59567
    },
    {
      "icon_id": "52680089",
      "name": "办证服务",
      "font_class": "banzhengfuwu",
      "unicode": "e8b1",
      "unicode_decimal": 59569
    },
    {
      "icon_id": "52680090",
      "name": "仓库",
      "font_class": "cangku",
      "unicode": "e8b2",
      "unicode_decimal": 59570
    },
    {
      "icon_id": "52680091",
      "name": "代办财税",
      "font_class": "daibancaishui",
      "unicode": "e8b3",
      "unicode_decimal": 59571
    },
    {
      "icon_id": "52680092",
      "name": "集装箱",
      "font_class": "jizhuangxiang",
      "unicode": "e8b4",
      "unicode_decimal": 59572
    },
    {
      "icon_id": "52680093",
      "name": "角标",
      "font_class": "jiaobiao",
      "unicode": "e8b5",
      "unicode_decimal": 59573
    },
    {
      "icon_id": "52680094",
      "name": "客户盘点",
      "font_class": "kehupandian",
      "unicode": "e8b6",
      "unicode_decimal": 59574
    },
    {
      "icon_id": "52680095",
      "name": "动态",
      "font_class": "dongtai",
      "unicode": "e8b7",
      "unicode_decimal": 59575
    },
    {
      "icon_id": "52680096",
      "name": "贷款",
      "font_class": "daikuan",
      "unicode": "e8b8",
      "unicode_decimal": 59576
    },
    {
      "icon_id": "52680097",
      "name": "生意经",
      "font_class": "shengyijing",
      "unicode": "e8b9",
      "unicode_decimal": 59577
    },
    {
      "icon_id": "52680098",
      "name": "结汇",
      "font_class": "jiehui",
      "unicode": "e8ba",
      "unicode_decimal": 59578
    },
    {
      "icon_id": "52680099",
      "name": "分层配置",
      "font_class": "fencengpeizhi",
      "unicode": "e8bb",
      "unicode_decimal": 59579
    },
    {
      "icon_id": "52680100",
      "name": "申请记录",
      "font_class": "shenqingjilu",
      "unicode": "e8bc",
      "unicode_decimal": 59580
    },
    {
      "icon_id": "52680101",
      "name": "上传备案单证",
      "font_class": "shangchuanbeiandanzheng",
      "unicode": "e8bd",
      "unicode_decimal": 59581
    },
    {
      "icon_id": "52680103",
      "name": "客户权益",
      "font_class": "kehuquanyi",
      "unicode": "e8bf",
      "unicode_decimal": 59583
    },
    {
      "icon_id": "52680105",
      "name": "权益配置",
      "font_class": "quanyipeizhi",
      "unicode": "e8c1",
      "unicode_decimal": 59585
    },
    {
      "icon_id": "52680106",
      "name": "双审",
      "font_class": "shuangshen",
      "unicode": "e8c2",
      "unicode_decimal": 59586
    },
    {
      "icon_id": "52680107",
      "name": "通关",
      "font_class": "tongguan",
      "unicode": "e8c3",
      "unicode_decimal": 59587
    },
    {
      "icon_id": "52680108",
      "name": "退税",
      "font_class": "tuishui",
      "unicode": "e8c4",
      "unicode_decimal": 59588
    },
    {
      "icon_id": "52680109",
      "name": "通关数据",
      "font_class": "tongguanshuju",
      "unicode": "e8c5",
      "unicode_decimal": 59589
    },
    {
      "icon_id": "52680110",
      "name": "快递物流",
      "font_class": "kuaidiwuliu",
      "unicode": "e8c6",
      "unicode_decimal": 59590
    },
    {
      "icon_id": "52680111",
      "name": "物流产品",
      "font_class": "wuliuchanpin",
      "unicode": "e8c7",
      "unicode_decimal": 59591
    },
    {
      "icon_id": "52680112",
      "name": "外汇数据",
      "font_class": "waihuishuju",
      "unicode": "e8c8",
      "unicode_decimal": 59592
    },
    {
      "icon_id": "52680113",
      "name": "信息bar_手机",
      "font_class": "xinxibar_shouji",
      "unicode": "e8c9",
      "unicode_decimal": 59593
    },
    {
      "icon_id": "52680114",
      "name": "新外综业务",
      "font_class": "xinwaizongyewu",
      "unicode": "e8ca",
      "unicode_decimal": 59594
    },
    {
      "icon_id": "52680115",
      "name": "物流订单",
      "font_class": "wuliudingdan",
      "unicode": "e8cb",
      "unicode_decimal": 59595
    },
    {
      "icon_id": "52680116",
      "name": "中间人",
      "font_class": "zhongjianren",
      "unicode": "e8cc",
      "unicode_decimal": 59596
    },
    {
      "icon_id": "52680117",
      "name": "信息bar_账户",
      "font_class": "xinxibar_zhanghu",
      "unicode": "e8cd",
      "unicode_decimal": 59597
    },
    {
      "icon_id": "52680118",
      "name": "一达通",
      "font_class": "yidatong",
      "unicode": "e8ce",
      "unicode_decimal": 59598
    },
    {
      "icon_id": "52680119",
      "name": "专业权威",
      "font_class": "zhuanyequanwei",
      "unicode": "e8cf",
      "unicode_decimal": 59599
    },
    {
      "icon_id": "52680120",
      "name": "账户操作",
      "font_class": "zhanghucaozuo",
      "unicode": "e8d0",
      "unicode_decimal": 59600
    },
    {
      "icon_id": "52680121",
      "name": "旋转90度",
      "font_class": "xuanzhuandu",
      "unicode": "e8d1",
      "unicode_decimal": 59601
    },
    {
      "icon_id": "52680122",
      "name": "退税融资",
      "font_class": "tuishuirongzi",
      "unicode": "e8d2",
      "unicode_decimal": 59602
    },
    {
      "icon_id": "52680123",
      "name": "Add Products",
      "font_class": "AddProducts",
      "unicode": "e8d3",
      "unicode_decimal": 59603
    },
    {
      "icon_id": "52680124",
      "name": "自营业务",
      "font_class": "ziyingyewu",
      "unicode": "e8d4",
      "unicode_decimal": 59604
    },
    {
      "icon_id": "52680125",
      "name": "addcell",
      "font_class": "addcell",
      "unicode": "e8d5",
      "unicode_decimal": 59605
    },
    {
      "icon_id": "52680126",
      "name": "background-color",
      "font_class": "background-color",
      "unicode": "e8d6",
      "unicode_decimal": 59606
    },
    {
      "icon_id": "52680127",
      "name": "cascades",
      "font_class": "cascades",
      "unicode": "e8d7",
      "unicode_decimal": 59607
    },
    {
      "icon_id": "52680128",
      "name": "beijing",
      "font_class": "beijing",
      "unicode": "e8d8",
      "unicode_decimal": 59608
    },
    {
      "icon_id": "52680129",
      "name": "bold",
      "font_class": "bold",
      "unicode": "e8d9",
      "unicode_decimal": 59609
    },
    {
      "icon_id": "52680130",
      "name": "资金",
      "font_class": "zijin",
      "unicode": "e8da",
      "unicode_decimal": 59610
    },
    {
      "icon_id": "52680131",
      "name": "eraser",
      "font_class": "eraser",
      "unicode": "e8db",
      "unicode_decimal": 59611
    },
    {
      "icon_id": "52680132",
      "name": "centeralignment",
      "font_class": "centeralignment",
      "unicode": "e8dc",
      "unicode_decimal": 59612
    },
    {
      "icon_id": "52680133",
      "name": "click",
      "font_class": "click",
      "unicode": "e8dd",
      "unicode_decimal": 59613
    },
    {
      "icon_id": "52680134",
      "name": "asp结算",
      "font_class": "aspjiesuan",
      "unicode": "e8de",
      "unicode_decimal": 59614
    },
    {
      "icon_id": "52680135",
      "name": "flag",
      "font_class": "flag",
      "unicode": "e8df",
      "unicode_decimal": 59615
    },
    {
      "icon_id": "52680136",
      "name": "falg-fill",
      "font_class": "falg-fill",
      "unicode": "e8e0",
      "unicode_decimal": 59616
    },
    {
      "icon_id": "52680137",
      "name": "Fee",
      "font_class": "Fee",
      "unicode": "e8e1",
      "unicode_decimal": 59617
    },
    {
      "icon_id": "52680138",
      "name": "filling",
      "font_class": "filling",
      "unicode": "e8e2",
      "unicode_decimal": 59618
    },
    {
      "icon_id": "52680139",
      "name": "Foreign currency",
      "font_class": "Foreigncurrency",
      "unicode": "e8e3",
      "unicode_decimal": 59619
    },
    {
      "icon_id": "52680140",
      "name": "guanliyuan",
      "font_class": "guanliyuan",
      "unicode": "e8e4",
      "unicode_decimal": 59620
    },
    {
      "icon_id": "52680141",
      "name": "language",
      "font_class": "language",
      "unicode": "e8e5",
      "unicode_decimal": 59621
    },
    {
      "icon_id": "52680142",
      "name": "leftalignment",
      "font_class": "leftalignment",
      "unicode": "e8e6",
      "unicode_decimal": 59622
    },
    {
      "icon_id": "52680143",
      "name": "extra-inquiries",
      "font_class": "extra-inquiries",
      "unicode": "e8e7",
      "unicode_decimal": 59623
    },
    {
      "icon_id": "52680145",
      "name": "pcm",
      "font_class": "pcm",
      "unicode": "e8e9",
      "unicode_decimal": 59625
    },
    {
      "icon_id": "52680146",
      "name": "reducecell",
      "font_class": "reducecell",
      "unicode": "e8ea",
      "unicode_decimal": 59626
    },
    {
      "icon_id": "52680147",
      "name": "rightalignment",
      "font_class": "rightalignment",
      "unicode": "e8eb",
      "unicode_decimal": 59627
    },
    {
      "icon_id": "52680148",
      "name": "pointerleft",
      "font_class": "pointerleft",
      "unicode": "e8ec",
      "unicode_decimal": 59628
    },
    {
      "icon_id": "52680149",
      "name": "subscript",
      "font_class": "subscript",
      "unicode": "e8ed",
      "unicode_decimal": 59629
    },
    {
      "icon_id": "52680150",
      "name": "square",
      "font_class": "square",
      "unicode": "e8ee",
      "unicode_decimal": 59630
    },
    {
      "icon_id": "52680151",
      "name": "superscript",
      "font_class": "superscript",
      "unicode": "e8ef",
      "unicode_decimal": 59631
    },
    {
      "icon_id": "52680153",
      "name": "单据转换",
      "font_class": "danjuzhuanhuan",
      "unicode": "e8f1",
      "unicode_decimal": 59633
    },
    {
      "icon_id": "52680154",
      "name": "Transfer money",
      "font_class": "Transfermoney",
      "unicode": "e8f2",
      "unicode_decimal": 59634
    },
    {
      "icon_id": "52680156",
      "name": "xiakuangxian",
      "font_class": "xiakuangxian",
      "unicode": "e8f4",
      "unicode_decimal": 59636
    },
    {
      "icon_id": "52680157",
      "name": "收起",
      "font_class": "shouqi",
      "unicode": "e8f5",
      "unicode_decimal": 59637
    },
    {
      "icon_id": "52680158",
      "name": "展开",
      "font_class": "zhankai",
      "unicode": "e8f6",
      "unicode_decimal": 59638
    },
    {
      "icon_id": "52680159",
      "name": "通讯录",
      "font_class": "tongxunlu",
      "unicode": "e8f7",
      "unicode_decimal": 59639
    },
    {
      "icon_id": "52680160",
      "name": "已关注供应商",
      "font_class": "yiguanzhugongyingshang",
      "unicode": "e8f8",
      "unicode_decimal": 59640
    },
    {
      "icon_id": "52680161",
      "name": "购买偏好",
      "font_class": "goumaipianhao",
      "unicode": "e8f9",
      "unicode_decimal": 59641
    },
    {
      "icon_id": "52680162",
      "name": "Subscribe",
      "font_class": "Subscribe",
      "unicode": "e8fa",
      "unicode_decimal": 59642
    },
    {
      "icon_id": "52680163",
      "name": "become a gold supplier",
      "font_class": "becomeagoldsupplier",
      "unicode": "e8fb",
      "unicode_decimal": 59643
    },
    {
      "icon_id": "52680164",
      "name": "new",
      "font_class": "new",
      "unicode": "e8fc",
      "unicode_decimal": 59644
    },
    {
      "icon_id": "52680165",
      "name": "free",
      "font_class": "free",
      "unicode": "e8fd",
      "unicode_decimal": 59645
    },
    {
      "icon_id": "52680166",
      "name": "cad-fill",
      "font_class": "cad-fill",
      "unicode": "e8fe",
      "unicode_decimal": 59646
    },
    {
      "icon_id": "52680167",
      "name": "robot",
      "font_class": "robot",
      "unicode": "e8ff",
      "unicode_decimal": 59647
    }
  ]
}
